setup.py
Similarity_udacity/Similarity.py
Similarity_udacity/__init__.py
Similarity_udacity/test_functions.py
Similarity_udacity.egg-info/PKG-INFO
Similarity_udacity.egg-info/SOURCES.txt
Similarity_udacity.egg-info/dependency_links.txt
Similarity_udacity.egg-info/not-zip-safe
Similarity_udacity.egg-info/top_level.txt