Metadata-Version: 1.0
Name: Similarity-udacity
Version: 0.0.4
Summary: Similarity Functions
Home-page: UNKNOWN
Author: rhys Jervis
Author-email: rhys.jervis94@gmail.com
License: UNKNOWN
Platform: UNKNOWN
